libit/Tron.py
libit/__init__.py
libit/asset.py
libit/bitcoin.py
libit/bs58.py
libit/coins.py
libit/lib.py
libit/reuse.py
libit/utils.py
libit/validate.py
libit/wallet.py
libit-5.3.6.dist-info/licenses/LICENCE
libit-5.3.6.dist-info/METADATA
libit-5.3.6.dist-info/WHEEL
libit-5.3.6.dist-info/top_level.txt
libit-5.3.6.dist-info/RECORD
