Metadata-Version: 2.4
Name: libit
Version: 5.3.6
Summary: Professional Bitcoin, Ethereum and Tron wallet generation library with support for multiple address formats
Home-page: https://libit.readthedocs.io/
Author: Mmdrza
Author-email: Mmdrza <Pymmdrza@gmail.com>
Maintainer-email: Mmdrza <Pymmdrza@gmail.com>
License: MIT
Project-URL: Homepage, https://github.com/pylibit/libit
Project-URL: Documentation, https://pylibit.github.io/libit/
Project-URL: Repository, https://github.com/pylibit/libit
Project-URL: Bug Tracker, https://github.com/pylibit/libit/issues
Project-URL: Changelog, https://github.com/pylibit/libit/blob/main/CHANGELOG.md
Keywords: bitcoin,ethereum,tron,cryptography,wallet,cryptocurrency,blockchain,private-key,address,p2pkh,p2sh,p2wpkh,p2wsh,segwit,bech32
Classifier: Development Status :: 5 - Production/Stable
Classifier: Intended Audience :: Developers
Classifier: License :: OSI Approved :: MIT License
Classifier: Operating System :: OS Independent
Classifier: Programming Language :: Python :: 3
Classifier: Programming Language :: Python :: 3.7
Classifier: Programming Language :: Python :: 3.8
Classifier: Programming Language :: Python :: 3.9
Classifier: Programming Language :: Python :: 3.10
Classifier: Programming Language :: Python :: 3.11
Classifier: Programming Language :: Python :: 3.12
Classifier: Topic :: Software Development :: Libraries :: Python Modules
Classifier: Topic :: Security :: Cryptography
Classifier: Topic :: Office/Business :: Financial
Requires-Python: >=3.7
License-File: LICENCE
Requires-Dist: pycryptodome>=3.15.0
Requires-Dist: ecdsa>=0.18.0
Provides-Extra: dev
Requires-Dist: pytest>=7.0.0; extra == "dev"
Requires-Dist: pytest-cov>=4.0.0; extra == "dev"
Requires-Dist: black>=22.0.0; extra == "dev"
Requires-Dist: flake8>=5.0.0; extra == "dev"
Requires-Dist: mypy>=0.991; extra == "dev"
Provides-Extra: docs
Requires-Dist: sphinx>=5.0.0; extra == "docs"
Requires-Dist: sphinx-rtd-theme>=1.0.0; extra == "docs"
Provides-Extra: enhanced
Requires-Dist: mnemonic>=0.20; extra == "enhanced"
Requires-Dist: hdwallet>=2.2.1; extra == "enhanced"
Requires-Dist: qrcode>=7.3.1; extra == "enhanced"
Dynamic: author
Dynamic: home-page
Dynamic: license-file
Dynamic: requires-python
